SwingedgeCore/__init__.py
SwingedgeCore/cloud/__init__.py
SwingedgeCore/cloud/Azure/__init__.py
SwingedgeCore/cloud/aws/__init__.py
SwingedgeCore/cloud/aws/sqs.py
SwingedgeCore/strategies/Candles.py
SwingedgeCore/strategies/DB.py
SwingedgeCore/strategies/__init__.py
SwingedgeCore-0.4.dist-info/METADATA
SwingedgeCore-0.4.dist-info/WHEEL
SwingedgeCore-0.4.dist-info/top_level.txt
SwingedgeCore-0.4.dist-info/RECORD
