Metadata-Version: 2.1
Name: SwingedgeCore
Version: 0.4
Summary: A package for utility functions used in SwingEdge Project
Home-page: https://github.com/dhirs/swingedge_core
Author: Syptus
Author-email: info@syptus.com
Requires-Dist: boto3
